setup.py
imhotep_jscs/__init__.py
imhotep_jscs/plugin.py
imhotep_jscs/plugin_test.py
imhotep_jscs.egg-info/PKG-INFO
imhotep_jscs.egg-info/SOURCES.txt
imhotep_jscs.egg-info/dependency_links.txt
imhotep_jscs.egg-info/entry_points.txt
imhotep_jscs.egg-info/requires.txt
imhotep_jscs.egg-info/top_level.txt