Metadata-Version: 1.0
Name: imhotep-jscs
Version: 0.0.2
Summary: An imhotep plugin for jscs validation
Home-page: https://github.com/justinabrahms/imhotep_jscs
Author: Justin Abrahms
Author-email: justin@abrah.ms
License: MIT
Platform: UNKNOWN
